{
  "wei18754": {
    "repos": [
      "Overjumborepotest1",
      "jumborepotest1",
      "TestEmptyRepo",
      "EmptyRepoTest",
      "TestGit2",
      "TestGit",
      "gandyge3supremomono",
      "TestNew",
      "Test23",
      "lilyweiNew",
      "enterpriselocal",
      "lilywei1supremomono",
      "lilyweiTestGit",
      "lilyweisupre",
      "lilyweiNewFull",
      "enterprise",
      "raghavendramooram1",
      "lilyweisupremomono",
      "lilywei1supre",
      "testGitRepo",
      "Trie",
      "composer-sample-applications",
      "tensorflow",
      "aquaponic"
    ],
    "followers": [],
    "following": [
      "firelotto"
    ]
  },
  "emails": []
}