{
  "TAbdiukov": {
    "repos": [
      "CISSP-YA-mnemonics",
      "img2pdf_helper",
      "safetynet-fix",
      "accommodations-web-portal",
      "Ikejime",
      "Microsoft-TrainingDays",
      "Exploit-DB",
      "PPSSPP-patches",
      "cissp-mind-map",
      "log4j-scan",
      "textgenrnn",
      "simple_capture",
      "Navman_MOVE75_Unlock_and_iGO",
      "Reverse_CryptoChecker",
      "dotfiles",
      "SecLists",
      "Pymem",
      "European-Nostarchpress",
      "lighthouse",
      "pwintools-samples",
      "pwintools",
      "kobo-book-downloader",
      "COVIDSafe-data",
      "AMC_patcher-CLI",
      "slack-portable-1",
      "dnsrecon",
      "gentext",
      "nostarchpress_blackfriday2019",
      "danneo-tools",
      "exe2wordsize"
    ],
    "followers": [],
    "following": [
      "AndrewRathbun",
      "DerreckM",
      "ukrainian-github",
      "vald-phoenix",
      "vshymanskyy",
      "lowpriority",
      "Amaranese",
      "M0n7y5",
      "tim545",
      "abbodi1406",
      "Micsullivan",
      "asymworks",
      "mithro",
      "rmaloney1",
      "jordanmiracle",
      "sickcodes",
      "jhaddix",
      "KrisKCode",
      "jan-kiszka",
      "theboy181",
      "aghorler",
      "BR0kEN-",
      "LachJones",
      "StepS-",
      "u17zl",
      "cry",
      "DK22Pac",
      "NABN00B",
      "cschramm",
      "adamtanana",
      "WearyMonkey",
      "faintx4",
      "wezham",
      "ttuanho",
      "WopsS",
      "denis0826",
      "mike-lischke",
      "cRAYonhere"
    ]
  },
  "emails": []
}