{
  "lowerrandom": {
    "repos": [
      "sleepy-puppy",
      "public-pentesting-reports",
      "SecLists",
      "Neurax",
      "IntelOwl",
      "Sparrow---CISA",
      "GHunt",
      "theZoo",
      "websploit",
      "h4cker",
      "PayloadsAllTheThings",
      "Default-Credentials",
      "Checklists",
      "LinEnum",
      "proxychains",
      "PlumHound",
      "APT-Lab-Terraform",
      "-LABPACK-",
      "AtomicPurpleTeam",
      "APT-Lab-FastOpticsSetup",
      "APTv4_Defcon28",
      "AutoSPFRecon",
      "-PlumHound-Tasks-",
      "dolib-images",
      "ps-whitenoiseweb",
      "DomainBuildScripts",
      "APT06202001",
      "LunarBadge",
      "DC27PartyBadge",
      "stringsifter"
    ],
    "followers": [],
    "following": []
  },
  "emails": []
}