{
  "luketainton": {
    "repos": [
      "luketainton",
      "FHeD",
      "PwnedPW",
      "hesk-docker",
      "pypilot",
      "epage",
      "template-go",
      "testing",
      "opensource.builders",
      "template",
      "luketainton.github.io",
      "warpd-docker",
      "6to4_converter",
      "iPilot",
      "go-complete-class",
      "publish-extensions",
      "documize-docker",
      "pyats-examples",
      "Traind",
      "dissertation",
      "TrumpTweets-Python",
      "CatFacts",
      "URLS",
      "pushover",
      "TrumpTweets-PHP",
      "TeamsUserEnroller",
      "lyrics",
      "aviary.sh"
    ],
    "followers": [],
    "following": [
      "kmanwar89",
      "tdeckers",
      "ChrisTitusTech",
      "louislam",
      "joshsmithy",
      "AlexxIT",
      "dchidell",
      "nickrusso42518",
      "dalhundal",
      "mohitudupa",
      "tomkerkhove",
      "PySimpleGUI",
      "InherentMac",
      "JamieEC",
      "msaaddev",
      "ahmadawais",
      "ajlkn",
      "mikepound",
      "kaya3",
      "brunojrpi",
      "jskinner97",
      "hak5darren",
      "gharris98",
      "torvalds",
      "AlterRock",
      "dcdoolan",
      "AndreiTuta",
      "AlexanderEDavis",
      "alexwileyy",
      "michaelsenior",
      "edwards070",
      "TSeelig",
      "PandelisZ",
      "bnang"
    ]
  },
  "emails": []
}