{
  "G4rb3n": {
    "repos": [
      "G4rb3n",
      "ThreatHunting-Book",
      "Arduino-Code",
      "Malware-Picture",
      "Botnet-Zoo",
      "Malbox",
      "Hunting-Book",
      "Script-Ganker",
      "Audit-Parser",
      "Malware-EVTX",
      "IoT_Sec_Tutorial",
      "Python-Code",
      "MD5-Calculator",
      "Windows-Driver",
      "Notes"
    ],
    "followers": [
      "RanR3n",
      "Dontjustadream",
      "revercc",
      "Th0rpe",
      "Squirre17",
      "toum120",
      "Unknown404-bot",
      "kunpen",
      "KKKRGZ",
      "0000000100000000",
      "aspenmayer",
      "BlackJack0",
      "GreyDr34d",
      "yhaolc",
      "LinWin-Cloud",
      "cl4ym0re",
      "wslxy",
      "cdhe",
      "NuclearEris",
      "Tian2000",
      "Lay0us1",
      "wooyin",
      "LoveCppp",
      "123dayu",
      "SmllXzBZ",
      "login546",
      "T0w3n",
      "f0ng",
      "Jumbo-WJB",
      "dksslq",
      "Evilran",
      "esin"
    ],
    "following": [
      "The-DFIR-Report",
      "rootclay",
      "Cyb3rWard0g",
      "decalage2",
      "hasherezade",
      "DidierStevens",
      "blackorbird",
      "NYAN-x-CAT",
      "aaaddress1",
      "pandazheng",
      "secrary",
      "suvllian",
      "Neo23x0"
    ]
  },
  "emails": [
    "979784643@qq.com",
    "85398@sangfor.com",
    "garbenvan@gmail.com"
  ]
}