{
  "RahulSharma-10": {
    "repos": [
      "BabyPlant-Final",
      "FirstWebsiteSupportingFiles",
      "FirstFullStackWebsite",
      "BabyPlant",
      "mojek",
      "NFTGenerator_NodeJS",
      "ChakraCore",
      "NGOWebsite",
      "AgniWebsite",
      "covid-resources-client",
      "FaceDetectApp",
      "C-Data-Structures-Algorithms",
      "ScreenShareEasy",
      "ColorGame",
      "Joke-TextToSpeech",
      "ImageInfinity",
      "QuoteGenerator",
      "FindYourFriends",
      "ToDoList"
    ],
    "followers": [],
    "following": [
      "taz71191",
      "utkarshgupta2504",
      "gauravmadan583",
      "dhruvbhrdwj",
      "saksham-kapoor",
      "ritviknagpal48",
      "arrohit258",
      "taruvar-mittal",
      "pranjaljain584",
      "Pallavbh23",
      "Yajassardana"
    ]
  },
  "emails": []
}