{
  "Hasan-Kilici": {
    "repos": [],
    "followers": [],
    "following": [
      "Siyami67",
      "f6c5",
      "Rich-Harris",
      "elsalvadordali",
      "Cuuss",
      "ahmtcn123",
      "ArdaDnmz",
      "HasanKlncc",
      "erenkulaksiz",
      "Yefee8",
      "06ergin06",
      "BilalAlpaslan",
      "benerenla",
      "Nicat-dcw",
      "falsisdev",
      "sayed71",
      "mzffr0",
      "david-kariuki",
      "Kwynto",
      "sezerlucianturkmen",
      "dirambora",
      "Ondra9071",
      "Kazdev0",
      "ZyraPasa",
      "ramazaneris",
      "sveltejs",
      "TheArmagan",
      "redentdev",
      "kedi",
      "umut25",
      "xDarkShiny",
      "baturaydumann",
      "kaankutan",
      "furkancankar",
      "facebook",
      "Drackin",
      "sarptekbas",
      "SpongeBed81",
      "ahmetdurmus",
      "ardasamedcelik",
      "Mustafa-Mert-Akceylan",
      "Layona-x",
      "kardespro"
    ]
  },
  "emails": []
}