{
  "NemesisWasAlienToo": {
    "repos": [
      "CoreKit",
      "c-c-_vscode_environment",
      "compile-time-regular-expressions",
      "HackTheBox",
      "STM32F10x",
      "CoreNodeFramework",
      "CoreNodeTranspiler"
    ],
    "followers": [
      "baajarmeh",
      "vishnu-qi",
      "TheBlackSheep3",
      "SuganthanBC",
      "ar-visions",
      "mrtzmhmmd",
      "yasin459",
      "WatchDogsDev",
      "taaraa99"
    ],
    "following": [
      "lefticus",
      "CppCon",
      "hanickadot",
      "ar-visions",
      "AnthonyCalandra",
      "YumcoderCom",
      "taaraa99",
      "WatchDogsDev"
    ]
  },
  "emails": []
}