{
  "luong-komorebi": {
    "repos": [
      "action-mailer-kafka",
      "algo",
      "Android-Contact-Example",
      "Android-Contact-Example-2",
      "api_on_rails",
      "archcolider",
      "asdf",
      "asdf-1",
      "async-bus",
      "Attack-Lab",
      "autoscaler",
      "awesome-agile",
      "Awesome-Linux-Software",
      "awesome-performance-testing",
      "aws-solutions-architect-associate-notes",
      "Begin-Latex-in-minutes",
      "betterspecs",
      "Binary-Bomb",
      "bitbucket-pipeline-aws-cloudfront-invalidate",
      "C-plus-plus-Data-Structure",
      "Calculator-App",
      "Canindex",
      "CanindexBackend",
      "Catch-The-Word",
      "charts",
      "cheatsheets",
      "CityWeatherForecast",
      "CKA-StudyGuide",
      "click-to-deploy",
      "contrib"
    ],
    "followers": [],
    "following": []
  },
  "emails": []
}