{
  "saleemrashid": {
    "repos": [
      "sha2-const",
      "sudo-cve-2019-18634",
      "binary-ff1",
      "unsafeless",
      "rust-bindgen",
      "mediatek_flash_tool",
      "nyt-2020-election-scraper",
      "html5-snake",
      "rmupdate",
      "pyemv",
      "simplehttpserver",
      "slack-emoji-maker",
      "redjubjub",
      "badecparams",
      "evilrouterlogin",
      "mypy",
      "twitter-punchcard",
      "EmailX",
      "changemac",
      "gcc-linaro-pkgbuild",
      "frida-sslkeylog",
      "is-this-a-pigeon",
      "operational-pgp",
      "ledger-mcu-backdoor",
      "iota-eu-cma",
      "do-i-need-a-blockchain",
      "trezor-debug",
      "nem-trezor-standalone",
      "python-windows-scripts",
      "pebble-libopencm3"
    ],
    "followers": [],
    "following": []
  },
  "emails": []
}