{
  "1ay1": {
    "repos": [
      "SRGP",
      "minix",
      "adminjs-design-system",
      "impact_run",
      "ed_facade",
      "RTableBooking",
      "nodejs-express-on-aws-ec2",
      "ADTs",
      "converse.js",
      "vscode-haskell",
      "nextjs-netlify-blog-template",
      "shotpy",
      "adminjs-upload",
      "purple-facebook",
      "purple-discord",
      "purple-matrix",
      "covid_care_frontend",
      "glib_demo",
      "slack-libpurple",
      "telegram-purple",
      "openfire-pade-plugin",
      "Algo_Ds_Notes",
      "openfire-restAPI-plugin",
      "node_doc",
      "c-toxcore",
      "do-app",
      "admin-bro",
      "qemu_stm32",
      "Advanced-Android-WebView",
      "spruce"
    ],
    "followers": [],
    "following": [
      "theandrew168",
      "meemtomar",
      "sif"
    ]
  },
  "emails": []
}