{
  "adonespitogo": {
    "repos": [
      "nvim",
      "async-concat-with-sourcemaps",
      "hyper-express",
      "node-set-ip-address",
      "tmux",
      "uWebSockets.js",
      "he-serve-static",
      "speedtest",
      "null-ls.nvim",
      "rails",
      "angular-base64-upload",
      "groupdate",
      "node-isc-dhcp-server",
      "AdoBot-IO",
      "node-minify-all-js",
      "node-debs",
      "json-duplicate-key-handle",
      "PiShrink",
      "portal-test",
      "capistrano-sidekiq-systemd",
      "AdoBot",
      "vue-ladda",
      "cordova-res",
      "openwrt-node-packages",
      "mock-releases",
      "network-config",
      "rollup-plugin-image-base64",
      "web-portal",
      "lines-engine",
      "angular-env"
    ],
    "followers": [
      "saitawngpha",
      "learnwithjunaid",
      "StudyingCode03",
      "D3n1sNet",
      "pgangm",
      "johnfamouz",
      "PORSCHEGHUB",
      "technicalhayden",
      "preethamb97",
      "blackstorm0514",
      "shivanahmady",
      "fenazi22",
      "0xd0a",
      "th3net",
      "createITLee",
      "ShadyTollipop",
      "leekayden",
      "CHristine-jpg-hub",
      "mtbasanez",
      "sudhirs745",
      "sayrab",
      "chxnugs",
      "narayanr7",
      "gopalindians",
      "avboy1337",
      "rc-chuah"
    ],
    "following": []
  },
  "emails": []
}