{
  "smakonin": {
    "repos": [
      "nilmworkshop.org",
      "uDisagg",
      "metadata.institute",
      "smakonin.github.io",
      "ScholarHacks",
      "Metadata.PID",
      "nilmtk",
      "HUE.dataset",
      "ampds.org",
      "RAE.dataset",
      "TextAdventure",
      "python-novice-inflammation",
      "2018-03-20-fakeit",
      "SparseNILM",
      "setup.py",
      "nilm.ca",
      "ccece2016.org",
      "NEWCAS_2016",
      "AMPds",
      "TheanoFun",
      "GAIL",
      "CMPT165",
      "COBOLsRevenge",
      "ArdraddReturns",
      "HackAndSlash",
      "mccSMTP",
      "mccHTTP",
      "mccPing",
      "GetPOP",
      "YunPrecompiles"
    ],
    "followers": [],
    "following": [
      "steveyko",
      "amueller",
      "AllenDowney",
      "lgair",
      "Tuiliq",
      "nipunbatra",
      "JackKelly",
      "fredpopowich"
    ]
  },
  "emails": []
}