{
  "ctfhacker": {
    "repos": [
      "aoc2022",
      "dotfiles",
      "ni-rs",
      "vim-lcov",
      "dedupe_files",
      "kvm-ioctls",
      "tis100",
      "paintbrush",
      "LibAFL",
      "binja-rs",
      "hypervisor_tests",
      "adventofcode-2020",
      "reven2-resources",
      "templeantics",
      "maverick-macroquad",
      "boardgames-macroquad",
      "maverickcardgame",
      "previewgenerator",
      "EpicTreasure",
      "ipxe",
      "rand_romu",
      "atomics",
      "adventofcode-2019",
      "heist",
      "grammartest",
      "prng-benchmarks",
      "fzero_fuzzer",
      "guifuzz",
      "ctfhacker.github.io",
      "codecov"
    ],
    "followers": [],
    "following": [
      "amatus"
    ]
  },
  "emails": []
}