{
  "yjose": {
    "repos": [],
    "followers": [],
    "following": [
      "shadcn",
      "kmagiera",
      "expo",
      "marklawlor",
      "jamonholmgren",
      "gorhom",
      "nandorojo",
      "zoontek",
      "abumalick",
      "chrfalch",
      "EvanBacon",
      "oblador",
      "rickhanlonii",
      "kadikraman",
      "anymaniax",
      "bluebill1049",
      "mrousavy",
      "slorber",
      "wcandillon",
      "tannerlinsley",
      "Rahiche",
      "jaredpalmer",
      "yyx990803",
      "sindresorhus",
      "Ouissalwrb",
      "JefferyHus",
      "younesshakky",
      "mxstbr",
      "medyo",
      "Amine-H",
      "iMeriem",
      "soub4i",
      "getify",
      "sdras",
      "bigfanjs",
      "TheLarkInn",
      "SaraVieira",
      "KadarH",
      "kentcdodds",
      "addyosmani",
      "wesbos",
      "mo-mughrabi",
      "bvaughn",
      "gaearon",
      "Csimo"
    ]
  },
  "emails": []
}