{
  "jacob-baines": {
    "repos": [
      "elfparser",
      "vuln_disclosure",
      "metasploit-framework",
      "concealed_position",
      "routeros",
      "wireless_pcaps",
      "turnscan.js",
      "veralite_upnp_exploit_poc",
      "libtins",
      "wasm_challenge",
      "longtime-sunshine",
      "jit_obfuscation_poc",
      "kodi_scripts",
      "NMEA0183",
      "Libstreams",
      "fuzzface"
    ],
    "followers": [],
    "following": [
      "gclair",
      "reidmefirst",
      "slyd0g",
      "BigNerd95",
      "headlesszeke",
      "mbechler",
      "s0lst1c3",
      "superducktoes"
    ]
  },
  "emails": []
}