{
  "Fahrj": {
    "repos": [
      "scapy",
      "canmatrix",
      "reverse-ssh",
      "hacktricks",
      "fitnesse-html-util",
      "flight-reservation",
      "PayloadsAllTheThings",
      "thc-hydra"
    ],
    "followers": [
      "TrongChuongDao",
      "projectdp",
      "arc41t3ct",
      "INT2ECALL",
      "techishow",
      "Magicianred",
      "AlexisFlach",
      "esin",
      "Valmario",
      "vishnummv",
      "fahmifj",
      "abhijitch",
      "ryanbaxendale"
    ],
    "following": []
  },
  "emails": []
}