{
  "getkey": {
    "repos": [],
    "followers": [],
    "following": [
      "rcherp89",
      "edolstra",
      "simon-tiger",
      "wkwan",
      "Prokos",
      "ErikSom",
      "Richienb",
      "medvednikov",
      "erikdubbelboer",
      "Keevle",
      "mathiasbynens",
      "elizagamedev",
      "tobspr",
      "electronoora",
      "Benjaminsen",
      "useresu",
      "munificent",
      "jasonrohrer",
      "hamaluik",
      "ISSOtm",
      "iONinja",
      "jonmalave",
      "calmh",
      "shazow",
      "timbl",
      "ry",
      "topjohnwu",
      "Inspirateur",
      "ncase",
      "kokounet",
      "torifat",
      "ploum",
      "eevee",
      "Matheus28",
      "ncannasse",
      "mikolalysenko",
      "whitequark",
      "chiel",
      "timovn",
      "dunxen",
      "abulerforrest",
      "let-def",
      "rubiefawn",
      "BurntSushi",
      "Rich-Harris"
    ]
  },
  "emails": []
}