{
  "k1R4": {
    "repos": [
      "deathnot3",
      "dotfiles",
      "simplepwnsolver",
      "k1r4.github.io",
      "Pwn",
      "RE",
      "WriteUps",
      "jekyll-theme-console",
      "demoji",
      "evanescet",
      "boomer-bob",
      "hacktoberfest-20"
    ],
    "followers": [],
    "following": [
      "santr4",
      "saumy4854",
      "manoj1749",
      "ar-seven",
      "Pwn-Solo",
      "abhikrishnaram",
      "SanjayVardhan",
      "Prashant9683",
      "yadhukrishnam",
      "PranavKrishnan007",
      "Akshaj000",
      "hitaarthh",
      "yakatyansh",
      "fr1gh7",
      "yasharora102",
      "rid1dle",
      "ProPlayerPlayz",
      "zardus",
      "souragc",
      "adityaradk",
      "thehyperpineapple",
      "officialcjunior",
      "d4rk-kn1gh7",
      "PwnVerse",
      "stuxnet999",
      "a3X3k",
      "GrimWatch",
      "nitinravi",
      "R3x",
      "haranrk",
      "cubetastic33",
      "AmunRha",
      "yashk2000",
      "aswinshenoy",
      "Mayukhdeb",
      "ashwinkey04",
      "vchrombie"
    ]
  },
  "emails": []
}