{
  "ragibson": {
    "repos": [
      "ragibson",
      "ModularityPruning",
      "Steganography",
      "scipy",
      "levy-stable-benchmarks",
      "leidenalg",
      "real-time-simulator",
      "DRRRT-motion-planning",
      "exalted-roller",
      "MFCC-speech-recognition",
      "CUDA-k-means",
      "linux-page-fault-experiment",
      "miniJava-compiler",
      "FPGA-Asteroids",
      "Rphenograph",
      "MedUCate"
    ],
    "followers": [],
    "following": [
      "kspalaiologos",
      "gvanrossum",
      "cjgibson"
    ]
  },
  "emails": []
}