{
  "guillaC": {
    "repos": [],
    "followers": [],
    "following": [
      "Xyl2k",
      "petikvx",
      "phra",
      "DoctorLai",
      "JohnHammond",
      "dr4k0nia",
      "SylvainSoKette",
      "ssl",
      "mitsukarenai",
      "Nyarime",
      "RyzenElstra",
      "SkyEmie",
      "DrayNeur",
      "ClubPanique",
      "michel-pi",
      "TonyCois",
      "otya128",
      "NinonTz",
      "LostInBrittany",
      "AdriPhilip",
      "KristenJestin",
      "sebdraven",
      "dzzie",
      "pigeonhands",
      "maaaaz",
      "gronoff",
      "Bencor29",
      "Audie80",
      "SvenLC",
      "CodeOfDark",
      "NYAN-x-CAT",
      "DimitriFourny",
      "Tuhinshubhra",
      "the0d3v",
      "UN5T48L3",
      "bytecode77",
      "danielbohannon"
    ]
  },
  "emails": []
}