{
  "JoshuaMart": {
    "repos": [
      "JoshuaMart",
      "www.jomar.fr",
      "httpx",
      "PwnedPasswordsChecker",
      "AutoRecon",
      "AutoScan",
      "HIBP_PasswordList_Slimmer"
    ],
    "followers": [
      "cocoonkid",
      "saadazghour",
      "Y00x",
      "cumsoft",
      "xSxFxLxHaKer",
      "zer0yu",
      "codex009",
      "CarlosJordanDev",
      "izdiwho",
      "sashka3076",
      "Diaa-Hassan",
      "Argonauta666",
      "stnv",
      "scumdestroy",
      "cxzero",
      "KinakoExE",
      "techishow",
      "0xSaltyHash",
      "harshtya9i",
      "tequreq",
      "Yunus96",
      "Faares",
      "CuPidev",
      "Hollow667",
      "OviKing123",
      "Rbcafe",
      "pager5Cx415Cx415Cx69",
      "elyasrz",
      "4cecod3",
      "sergiuvinc"
    ],
    "following": [
      "jcolfej"
    ]
  },
  "emails": []
}