{
  "Tarjei400": {
    "repos": [
      "simple-scroller",
      "einsteinrosen",
      "fe-playground",
      "debezium-examples",
      "etoro-api",
      "bitnami-docker-postgresql",
      "sse-flink-poc",
      "config-event-bus-nestjs",
      "flink",
      "charts-1",
      "lerna",
      "oatpp-consul",
      "conan-caf",
      "conan-center-index",
      "actor-framework-experiments",
      "conan-packages",
      "conan-civetweb",
      "ppconsul",
      "video-streaming-service",
      "cpp-caf-experiment",
      "jenkins-shared-libraries",
      "aws-sdk-cpp",
      "fluent-plugin-sqs",
      "components",
      "openvpn-docker",
      "jsonforms",
      "glfw",
      "netcat",
      "goofys",
      "necronia-keycloak-theme"
    ],
    "followers": [],
    "following": [
      "mjraadi",
      "hrsantiago",
      "edubart"
    ]
  },
  "emails": []
}