{
  "pirate": {
    "repos": [
      "public-web-archives",
      "Mailu",
      "mercury-parser",
      "txmoderna.com",
      "bash-utils",
      "wireguard-docs",
      "sping",
      "ArcMini",
      "archivebox-codespace",
      "docker-samba-timemachine",
      "django-huey-monitor",
      "send",
      "send-docker-compose",
      "storj",
      "cloudflare-docs",
      "wikipedia-mirror",
      "cpython",
      "quebec-power-grid-talk",
      "mesh-botnet",
      "docker-templates",
      "Cpp-Data-Structures",
      "mac-keyboard-brightness",
      "sentry-docs",
      "WebRTCChat",
      "nicksweeting.com",
      "gzint",
      "stdeb",
      "internet-archiving-talk",
      "spellchecker",
      "fish-utils"
    ],
    "followers": [],
    "following": [
      "alok",
      "socketteer",
      "pganssle",
      "doy",
      "elo-siema",
      "asanchezyali",
      "curibe",
      "juanArias8",
      "MirjamJG",
      "Firfi",
      "Joyce-O",
      "smankovsky",
      "sobri909",
      "evancasey",
      "ncase",
      "CtrlSpice",
      "TomLisankie",
      "andrewmusk",
      "siraben",
      "krobelus",
      "tjhorner",
      "jbrew",
      "upsuper",
      "majek",
      "danielhodson",
      "Uzay-G",
      "astraw",
      "jamesgui",
      "mAAdhaTTah",
      "b5",
      "crawshaw",
      "alex-segura",
      "tmcw",
      "adam-cowley",
      "hawkrives",
      "asbiin",
      "djaiss",
      "krisnova",
      "tianon",
      "benmkw",
      "behlendorf",
      "catilac",
      "freakboy3742",
      "imlonghao",
      "zhiyue"
    ]
  },
  "emails": [
    "githubpirate@gmail.com",
    "nikisweeting@gmail.com",
    "git@nicksweeting.com",
    "nickwentboom@gmail.com",
    "git@sweeting.me"
  ]
}