{
  "PandeoF1": {
    "repos": [
      "PandeoF1",
      "42-ft_containers",
      "px_ssh",
      "px_botnet",
      "42-webserv",
      "42-libft",
      "42-cub3d",
      "42-minishell",
      "42-inception",
      "Portfolio-Manager",
      "ft_free",
      "42-piscine",
      "42-philosophers",
      "Portfolio",
      "42-minitalk",
      "pandeo.fr",
      "42-push_swap",
      "42-so_long",
      "42-get_next_line",
      "42-rush-ai",
      "42-ft_printf",
      "makefile",
      "ticket-manager",
      "monitoring"
    ],
    "followers": [],
    "following": [
      "JeremyBosquet",
      "AshitakaYT",
      "DynAlexotron",
      "electr0lulz",
      "kachayev",
      "42School",
      "b-moulin",
      "Theoted",
      "Adonissfy",
      "Qwazertyx",
      "WhiteHoodHacker",
      "Nextwab",
      "Azenet",
      "NYAN-x-CAT"
    ]
  },
  "emails": [
    "theo.nard18@gmail.com",
    "58373303+PandeoF1@users.noreply.github.com",
    "49699333+dependabot[bot]@users.noreply.github.com",
    "clementplanque@gmail.com",
    "regissantos300@gmail.com",
    "42345020+xxloubexx@users.noreply.github.com"
  ]
}