{
  "lightsofapollo": {
    "repos": [
      "js-libp2p-webrtc",
      "joi-to-json-schema",
      "git-repo",
      "iai",
      "glommio",
      "rust-bindgen",
      "socket-retry-connect",
      "amundsenfrontendlibrary",
      "pulumi-awsx",
      "jest-github-action",
      "react-grid-layout",
      "webrtc",
      "srtp",
      "dorsvr",
      "rtp",
      "react-use",
      "solana",
      "gitea",
      "RustPython",
      "webpack-config-plugins",
      "docs",
      "environment-razorstump-production",
      "environment-razorstump-staging",
      "autoscaler",
      "serverless-appsync-plugin",
      "velocity.js",
      "aws-mobile-appsync-sdk-js",
      "superagent-promise",
      "json-templater",
      "node-pureimage"
    ],
    "followers": [],
    "following": [
      "ckousik",
      "sathishcaffeine",
      "ScottSavarie",
      "danielsht86",
      "iammai",
      "aidylka",
      "plauche",
      "kripken",
      "adetaylor",
      "RReverser",
      "sindresorhus",
      "artokun",
      "jimporter",
      "Sean-Der",
      "sid88in",
      "kyleparrott",
      "gilbert",
      "nickdesaulniers",
      "mikehenrty",
      "dherman",
      "gordonbrander",
      "forresti",
      "alexcrichton",
      "snowmantw",
      "ForbesLindesay",
      "KevinGrandon",
      "runeh",
      "clanam",
      "taylornrolyat",
      "camme",
      "andreasgal",
      "LeaVerou",
      "jeremyosborne",
      "MarcelloDuarte",
      "ericf",
      "tj",
      "rauchg",
      "josevalim",
      "isaacs",
      "twerth",
      "rgrove",
      "wycats"
    ]
  },
  "emails": []
}