{
  "Brayconn": {
    "repos": [],
    "followers": [],
    "following": [
      "ircluzar",
      "LostNintendoHistory",
      "ruffle-rs",
      "cave-story-randomizer",
      "TheScienceElf",
      "TLinkan",
      "Vukkyy",
      "NCommander",
      "MechanoPixel",
      "oldnewthing",
      "kiatus",
      "xoreaxeaxeax",
      "MeguminSama",
      "Giftfox",
      "periwinkle9",
      "nezza",
      "aarmastah",
      "magcius",
      "wert23239",
      "ReRezd",
      "zippy731",
      "jozsefsallai",
      "TrashboxBobylev",
      "ChristopherRathmam",
      "calvarado194",
      "GabrielRavier",
      "IsoFrieze",
      "ichordev",
      "thomas-xin",
      "Carrotlord",
      "deviantollam"
    ]
  },
  "emails": []
}