{
  "rvrsh3ll": {
    "repos": [
      "Flipper",
      "PoC-in-GitHub",
      "enum4linux-ng",
      "atomic-red-team",
      "flipperzero-firmware",
      "PrivFu",
      "pyscript",
      "active-directory-dotnet-desktop-msgraph-v2",
      "Infosec_Reference",
      "trufflehog",
      "SysmonEoP",
      "theHarvester",
      "msportals.io",
      "Coercer",
      "Mangle",
      "nmap",
      "LavaMoat",
      "WinPwn",
      "DInvoke_rs",
      "CloudPentestCheatsheets",
      "FindUncommonShares",
      "impacket",
      "PSBits",
      "TeamFiltration",
      "ip2provider",
      "SilentHound",
      "bitcoinlib",
      "sliver",
      "Oh365UserFinder",
      "PayloadsAllTheThings"
    ],
    "followers": [],
    "following": [
      "futuresec-io",
      "zoldur",
      "kfosaaen",
      "digination",
      "toolswatch",
      "rsmudge",
      "splinterbotnet"
    ]
  },
  "emails": []
}