{
  "hirusha-adi": {
    "repos": [
      "Stealer-Pendrive",
      "Near",
      "Fuel-Availability",
      "Stalker",
      "GifGang",
      "Discord-Account-Always-Onlie",
      "Fortnite-Tracker-Discord-Bot",
      "Keylogger",
      "Keylogger-CPP",
      "InstaStalker",
      "Darkweb-Links",
      "Qt-Designer-Projects",
      "learning-cs50-computer-science",
      "hirusha",
      "OL-Past-Papers-Website-Sri-Lanka",
      "yourbot",
      "bsoderrorcodes",
      "Oxygen",
      "windows-11-setup-virus",
      "spam",
      "CV-Generator",
      "Market",
      "Windscribe-Checker",
      "NordVPN-Checker",
      "MusicBot",
      "PDF-password-cracker",
      "Genode-Free-Proxies-API-Wrapper",
      "sonixd",
      "Ultimate-USB",
      "National-Fuel-Pass-Nativefied"
    ],
    "followers": [],
    "following": [
      "NothingOSS",
      "dhanushkac",
      "Vanilla-OS",
      "NYAN-x-CAT",
      "BlackArch",
      "choozn",
      "gayanvoice",
      "AYIDouble",
      "nimash3eshan",
      "dmalan",
      "isomerpages",
      "sandarutharuneth",
      "Dex-404",
      "ThenuSand",
      "mxschmitt",
      "Personal-Linux-Scripts",
      "ForrestKnight",
      "OLIVER8903",
      "Pradumnasaraf",
      "lita",
      "ImNotAVirus",
      "Thammus",
      "KalobTaulien",
      "GitHubExperts-LK",
      "avincodes",
      "L0calSerVe4",
      "crustymonkey",
      "ItsHisoka17",
      "megasanjay",
      "chunkydonut21",
      "bpasero",
      "josh",
      "devrimos",
      "DanielGleich",
      "hash3liZer",
      "x4nth055",
      "thelecter",
      "taylorotwell",
      "Cyberlytical",
      "SharonIV0x86",
      "diddledani",
      "TheRealZago",
      "FlyTechVideos",
      "BroadbentT",
      "BlueManCZ"
    ]
  },
  "emails": []
}