{
  "javascript-obfuscator": {
    "repos": [],
    "followers": [
      "fireword",
      "dvanh199",
      "LukokiMakuntimaDaniel",
      "LoboMix11",
      "zlabs",
      "szarca",
      "ulilalbab",
      "m0ham3dx",
      "masx200",
      "moteesh-in2tive",
      "godxkey",
      "dittyBox",
      "LeroyK111",
      "bigpanda79",
      "Brainhub24",
      "SACHINnANYAKKARA",
      "Fangzbotz2007",
      "abu3389",
      "dypblue",
      "Exodiel",
      "mkdirnow",
      "topmaster716",
      "jkin8010",
      "frusanov",
      "HiColinSong",
      "Keystion",
      "masdimya"
    ],
    "following": []
  },
  "emails": []
}