{
  "sahilskumar": {
    "repos": [
      "Tapsearch",
      "Music-Recommender-System",
      "450-DSA-Tracker",
      "Implementation",
      "python-aria-mirror-bot",
      "educative.io_courses",
      "G-Index",
      "embetacloud",
      "DBMS-PROJECT",
      "SPOJ-SOLUTIONS",
      "Reddit-Sentimental-Analysis",
      "Recommendation-Engine",
      "Color-Game",
      "A8-PID-CONTROLLER",
      "Deep-Learning",
      "Distributed-Hash-Tables",
      "Share_Extension"
    ],
    "followers": [],
    "following": [
      "surya-veer",
      "HasibulKabir",
      "kalpitdixit",
      "tanaikech",
      "sindresorhus",
      "pprathameshmore"
    ]
  },
  "emails": []
}