{
  "jandersoncampelo": {
    "repos": [
      "ABP-ToDoApp",
      "JCExpensesTracker",
      "Weather-Forecast-Microservice",
      "to-do_react-app",
      "BeerService",
      "DesafioJurosComposto",
      "SrtSync",
      "jandersoncampelo",
      "InfosecBookmarks",
      "dev-fitness",
      "jandersoncampelo.github.io"
    ],
    "followers": [
      "Optimussp",
      "brinhosa",
      "Surya-7777",
      "VBertuol",
      "BronnyWang",
      "vanessakoch",
      "maxamin",
      "pvcapuano",
      "Gil-2130",
      "hugocrosa",
      "GuilhermeEly10",
      "auriceliof",
      "Paulo0999",
      "caioagiani",
      "grassiricardo",
      "lira92",
      "brunohmelo"
    ],
    "following": [
      "endersonmenezes",
      "stebsnusch",
      "VBertuol",
      "ntxinh",
      "carlosItDevelop",
      "vanessakoch",
      "luizcarlosfaria",
      "fredimachado",
      "rodolformartins",
      "pvcapuano",
      "hugocrosa",
      "dirceuBarquette",
      "danielfs13",
      "auriceliof",
      "adrianoalves93",
      "rafaballerini",
      "incredibleindishell",
      "infosec-au",
      "daeken",
      "jhaddix",
      "jobertabma",
      "nahamsec",
      "sparcflow",
      "screetsec",
      "offensive-security",
      "nulsec",
      "estark37",
      "breakzplatform",
      "brunohmelo",
      "lira92",
      "guiigos",
      "fabiorogeriosj",
      "grassiricardo",
      "mateusortiz",
      "ocarloslopes",
      "ferfabricio"
    ]
  },
  "emails": []
}