{
  "n1ghtx0w1": {
    "repos": [
      "n1ghtx0w1.github.io",
      "a-plus-studying",
      "Walking-an-app",
      "intro-offensive-sec",
      "n1ghtx0w1",
      "sanity-app",
      "dropdown-menu",
      "vrising-app",
      "my-basic-app",
      "WriteUps",
      "blog-learning",
      "oracle-linux",
      "Blue-Team-Tools",
      "cool-cyber-project",
      "Windows-Optimize-Harden-Debloat"
    ],
    "followers": [],
    "following": [
      "Cyb3rA",
      "kautukkundan"
    ]
  },
  "emails": []
}