{
  "RajatGarg97": {
    "repos": [
      "Ubuntu-Clone",
      "RajatGarg97",
      "Msdyn365.Commerce.Online",
      "martonlederer",
      "SplitWiseTakeHomeAssignment",
      "macOSPortfolio",
      "Screen-Recorder",
      "docker-helloworld",
      "vivek9patel.github.io",
      "Community-Curated-Resources",
      "Ultimate-Python-Resource-Hub",
      "TheOdinProject",
      "developer-portfolios",
      "Backend-Infra",
      "url-shortener",
      "developerFolio",
      "tutorialdb",
      "scrroll-in",
      "CodingClubIndia",
      "myWebsite",
      "VideoChatApp",
      "personal-website",
      "educative.io_courses",
      "game_control",
      "ttt-1-welcome-rb-cb-gh-000",
      "hello-world-ruby-cb-gh-000",
      "your-first-lab-cb-gh-000",
      "katacoda-scenarios",
      "xabber-android",
      "Apollo-11"
    ],
    "followers": [],
    "following": [
      "arpitbbhayani",
      "Eazy-Develop-User-Repo",
      "ariya",
      "kdn251",
      "ChaiBapchya",
      "tssovi",
      "sindresorhus",
      "karthequian",
      "codediodeio",
      "arpansac",
      "MadhavBahl",
      "shoaibrayeen",
      "florinpop17",
      "kshitijmishra23",
      "vineetjohn",
      "Devang-25",
      "rakyll",
      "nickdesaulniers",
      "bradtraversy",
      "jeffrafter",
      "IamBia",
      "Dharni0607",
      "mrigesh",
      "kelseyhightower",
      "sachincool",
      "kootenpv",
      "nrsyed",
      "ViachKakovskyi",
      "gouthamve",
      "cuuupid",
      "ankit-rathi",
      "rachitiitr",
      "Manojkumarchow",
      "clarecorthell",
      "RubensZimbres",
      "shubhi-sareen",
      "WuJie1010",
      "xhuvom",
      "serengil",
      "yjucho1",
      "PiotrDabrowskey",
      "rasbt",
      "filannim",
      "aaqaishtyaq",
      "susheem-k-zz",
      "cprinzz"
    ]
  },
  "emails": []
}