{
  "LetUsFsck": {
    "repos": [
      "dex2jar",
      "MagicPacketGenerator",
      "UPNP-FUN",
      "haproxy",
      "iperf",
      "sniproxy",
      "PayloadsAllTheThings",
      "natcap",
      "irssi",
      "reqrypt",
      "nmap-nse-scripts",
      "killerbee",
      "Meltdown",
      "Z3sec",
      "GRR-docker",
      "PoC-Exploit-Mirror",
      "MirroredExploits",
      "WSC2",
      "Reptile",
      "iMessagesBackdoor",
      "protokill",
      "blueborne-scanner",
      "spray-system",
      "mirai",
      "ZLL_Lights",
      "WebTerror",
      "autoscraper",
      "Carberp",
      "Upnp-Exploiter",
      "tiny-tcp-scanner"
    ],
    "followers": [],
    "following": [
      "cldrn",
      "MSylvia",
      "dustyfresh",
      "dnoiz1",
      "0xricksanchez",
      "hook-s3c",
      "dumbbutgenius",
      "zer0yu",
      "BusesCanFly",
      "blacknbunny",
      "cedriczirtacic",
      "phikshun",
      "kaizoku",
      "netspooky",
      "deoxxa",
      "0x00-0x00",
      "WazeHell",
      "IoTsec",
      "gianlucaborello",
      "f0rb1dd3n",
      "Billy-Ellis",
      "Siguza",
      "m0nad",
      "DonnchaC",
      "notpike",
      "samyk",
      "ManicDevs",
      "gdbinit",
      "audiohacked",
      "haccer",
      "guilhermelimak",
      "geohot",
      "mobking33",
      "scalefree",
      "mattghali",
      "graves"
    ]
  },
  "emails": []
}