{
  "brett-fitz": {
    "repos": [
      "docs",
      "core",
      "pyMalleableProfileParser",
      "XLMMacroDeobfuscator",
      "manjusaka",
      "mkdocs-material",
      "traefik",
      "ecs",
      "C2-Servers",
      "malware-pcap",
      "docker-traefik",
      "pyMalleableProfileFinder",
      "PayloadsAllTheThings",
      "Malleable-C2-Profiles",
      "PrintNightmare",
      "myxxdev.github.io",
      "cobaltstrike",
      "pyjarm",
      "toml",
      "jarm",
      "commands-for-sec",
      "sifter",
      "hunter",
      "roadmap-generator",
      "notes",
      "docker-splunk-phantom",
      "python",
      "BritishSquare",
      "cte",
      "stego-toolkit"
    ],
    "followers": [],
    "following": [
      "jordan-wright",
      "hellofresh",
      "zcgonvh",
      "CrakingSoft",
      "9993rills",
      "NYAN-x-CAT",
      "moloch--",
      "toniblyx",
      "aaronst",
      "hatching",
      "pathtofile",
      "beskridge",
      "cedowens",
      "fitz003",
      "maxpl0it",
      "Riuchando"
    ]
  },
  "emails": []
}