{
  "developervariety": {
    "repos": [
      "\"/developervariety/secureapp\"",
      "\"/developervariety/pshield\""
    ],
    "followers": [
      "HRAlinaFI",
      "arsium",
      "H4X4U",
      "Turbski",
      "remotemachine1",
      "haootic",
      "BreakShoot",
      "novice",
      "MafujShikder",
      "Aekras1a",
      "mbautin",
      "okieeee"
    ],
    "following": [
      "jchristn",
      "Gskartwii",
      "BreakShoot",
      "zsr2531",
      "Zaczero",
      "Auralytical",
      "grandsilence",
      "pigeonhands",
      "NYAN-x-CAT",
      "yck1509",
      "holly-hacker",
      "XenocodeRCE",
      "TheProxyRE"
    ]
  },
  "emails": []
}