{
  "Einstrasse": {
    "repos": [
      "ckeditor5",
      "graduation_work",
      "ckeditor5-angular",
      "unlicense",
      "defcon-2021-smart-cryptooo",
      "srtmacro",
      "dnSpy",
      "babylontest",
      "leetcode",
      "samsung-q60t-exploit",
      "Einstrasse.github.io",
      "codedit-ui-js",
      "rustlings",
      "q1k3",
      "socket.io-client",
      "SummerFestival",
      "aps-studio",
      "react-electron-boilerplate",
      "AlgoStudy",
      "web-proxy.js",
      "rust-web-server",
      "hls-service",
      "mafia",
      "ctf-practice",
      "simple-sock-prog",
      "2019-Christmas-CTF",
      "js-vuln-db",
      "problem-solving",
      "MintOS64",
      "GUI-for-GoodbyeDPI"
    ],
    "followers": [],
    "following": [
      "dlehgus1023",
      "JinYoung-Shin",
      "Rob--W",
      "minhoryang",
      "ariya",
      "JonathanSalwan",
      "utilForever",
      "kdy1",
      "NicoHood",
      "Qwaz",
      "hhkers",
      "cs01",
      "wbowling",
      "pendoubleg",
      "scwuaptx",
      "ValdikSS",
      "push0ebp",
      "lifthrasiir",
      "ndb796",
      "mdsnins",
      "HeeillWang",
      "topjohnwu",
      "hahwul",
      "bluepichu",
      "egoing",
      "defparam",
      "lemmaa",
      "realsung",
      "crowell",
      "gentilkiwi",
      "orangetw",
      "monologg",
      "tsgates",
      "zizihacker",
      "kkamagui",
      "adm1nkyj",
      "junorouse",
      "luxroot",
      "ManHyuk",
      "junhee-ko",
      "wkdgusdn3",
      "hodoogwaja",
      "Jinmo"
    ]
  },
  "emails": []
}