{
  "Dos98": {
    "repos": [
      "drakvuf",
      "reports",
      "ThreatHunter-Playbook",
      "kernel-fuzzer-for-xen-project",
      "atomic-red-team",
      "strace",
      "gsoc19",
      "ProcessInjectionTechniques",
      "Detecting-Malware-using-Ensemble-Method-based-on-DNN",
      "libvmi",
      "awesome-malware-analysis",
      "rekall",
      "Malware-Classificaion-basics",
      "Digit-Recognizer-Kaggle",
      "firebase-basics",
      "contacts-database",
      "crypto-project",
      "angular-2-basics",
      "work",
      "zulip-electron",
      "simulator",
      "coypu",
      "hotel_management_sys",
      "bulma-templates",
      "functions-samples",
      "newsletter2",
      "myfirstRes",
      "Image-Processing"
    ],
    "followers": [],
    "following": [
      "thekensingtonschool",
      "r4j0x00",
      "FuzzySecurity",
      "adamziaja",
      "mrexodia",
      "itm4n",
      "k-vitali",
      "subhashdasyam",
      "icedevml",
      "deepakchethan",
      "radare",
      "mleinhos",
      "sladyn98",
      "tklengyel",
      "Wenzel",
      "disaykin",
      "0xRick",
      "akshaykumar90",
      "maxpumperla",
      "fchollet",
      "akshitgrover",
      "pradyunsg",
      "nishnash54",
      "marceloschmidt",
      "felixrieseberg",
      "feross",
      "codebytere",
      "anantlk",
      "Presto412",
      "chris-sev",
      "cornflourblue",
      "tstreamDOTh",
      "Vishwajeetsinh98",
      "dshubhadeep",
      "ashwini0529",
      "nicolasgarnier",
      "kunagpal",
      "hvarday",
      "AnanduSreekumar",
      "manmeet17"
    ]
  },
  "emails": []
}