{
  "x00null": {
    "repos": [
      "juice-shop",
      "forward-shell",
      "keepnote",
      "web_crawler",
      "fuzzer",
      "backdoor",
      "keylogger",
      "arp_spoof_detector",
      "code_inject",
      "packet_sniffer",
      "dns_spoofer",
      "arp_spoofer",
      "evil_file",
      "network_scanner",
      "mac_changer",
      "Penetration-Testing-Study-Notes",
      "OSCP-2",
      "Features-X",
      "XposedInstaller",
      "nemesis",
      "Xposed-Extended-Power-Menu",
      "XposedBridge"
    ],
    "followers": [],
    "following": [
      "fuzzlove",
      "Entropy512"
    ]
  },
  "emails": []
}