{
  "lukestanley": {
    "repos": [
      "check_for_password_leaks",
      "grug-dev-translation",
      "kendraio-proxy",
      "ordinary-portal",
      "StyleCLIP",
      "homebrew-core",
      "exploring_uk_police_api",
      "three.py",
      "jitsi_mirror",
      "mobileFriendlyMasterPass",
      "test-ranking",
      "tutorial",
      "MeshDemocAgora",
      "wiki_pagerank",
      "cv_view",
      "emscripten_shedskin_setup",
      "emscripten",
      "yviz",
      "iscroll",
      "OTE-IDE",
      "try_git",
      "node-dht",
      "lustdb"
    ],
    "followers": [],
    "following": [
      "howardsandford",
      "maguayo",
      "riverssteve",
      "lucidrains",
      "r9y9",
      "echelon",
      "davestevens",
      "jrocketfingers",
      "MissMaximas",
      "LilyFoote",
      "niklasvh",
      "LionKimbro"
    ]
  },
  "emails": []
}