{
  "ivanandrianto": {
    "repos": [
      "YAFT",
      "YAFT-Jenkins-Plugin",
      "Android-SMS-App-with-Elliptical-Curve-Cryptography",
      "SentimentAnalysis",
      "Online-PPOB",
      "Sunshine-App",
      "Pengadaan-Pegawai",
      "IF3111-2016-Tugas1-Android",
      "Duktek-Inventory-Management-System",
      "Promo-Scrapper",
      "Biodict",
      "Local-Search-Engine",
      "Tweet-Hunt",
      "Web-Recruitment-ARC",
      "IF3110-2015-T1",
      "Tubes-1-Jarkom"
    ],
    "followers": [],
    "following": []
  },
  "emails": []
}