{
  "4n4nk3": {
    "repos": [
      "pyFlipper",
      "proxmark3",
      "flipperzero-firmware",
      "javascript-exercises",
      "hugo-theme-shell",
      "osed-scripts",
      "django-bootstrap-pagination",
      "skribbl-io-guesser",
      "HikPwn",
      "Wordlister",
      "HID",
      "django-pagination-bootstrap",
      "Mythic",
      "godoh",
      "hacktricks",
      "librarian",
      "gosharedlib",
      "TinkererShell",
      "poseidon",
      "KotLister",
      "BotOCRVideoWatcher",
      "PCAPtoPorts",
      "steganography",
      "python-scraping",
      "SimpleNessusParser",
      "ReflectiveDLLInjection",
      "pyxhook",
      "Duckuino"
    ],
    "followers": [],
    "following": [
      "evilsocket",
      "gcblauth",
      "REMitchell",
      "alessandroponzo"
    ]
  },
  "emails": []
}