{
  "0xmanhnv": {
    "repos": [
      "nguyenmanh-messager",
      "pentest-notes",
      "redteam-notes",
      "htb00",
      "KnowledgeSharing",
      "hacktricks",
      "accumulate-points",
      "AutoRecon",
      "RedTeam-OffensiveSecurity",
      "digitalbank-gen-one",
      "AllAboutBugBounty",
      "whale-tracker",
      "Awesome-Smart-Contract-Security",
      "Web-Attack-Cheat-Sheet",
      "go-binance-bot",
      "0xmanhnv",
      "0xmanhnv.github.io",
      "precommit-with-detect-secrets",
      "KingOfBugBountyTips",
      "cms-demo",
      "90DaysOfDevOps",
      "simplebank",
      "blockchain-development-guide",
      "ctf-writeups",
      "go-to-do-app",
      "ThreatMapper",
      "learn-web3-dapp",
      "pentest-book",
      "JSONBee",
      "awesome-cicd-security"
    ],
    "followers": [],
    "following": [
      "projectdiscovery",
      "neocotic",
      "greatbn",
      "ducpx",
      "ManhNho",
      "researchersource",
      "phanan",
      "huent-1493",
      "dactoankmapydev",
      "ZuzooVn"
    ]
  },
  "emails": []
}