{
  "varunp2k": {
    "repos": [],
    "followers": [],
    "following": [
      "P6-36-216",
      "dodiku",
      "lucidrains",
      "Shahabks",
      "Rohit4352",
      "LeeKLTW",
      "anujgupta82",
      "ameyabhamare",
      "jayanarayanan",
      "AshishAsokan",
      "yk",
      "Ojjie",
      "RuchikaShashidhara",
      "bhargavsk1077",
      "pranav-bhatt",
      "thomwolf",
      "RITIKHARIANI",
      "suranah",
      "shreyash14s",
      "NaikAayush",
      "kartikay-bagla",
      "psiayn",
      "Abhishek262",
      "nsankethreddy",
      "ManuMBhat",
      "Kriyszig",
      "nishkalavallabhi",
      "metonymic-smokey",
      "RaghavRoy145",
      "chandratop",
      "shishir610",
      "ThrivikramanV",
      "temanisparsh",
      "Samyak2",
      "siddhantrao23",
      "Gituser143"
    ]
  },
  "emails": []
}