{
  "heungheung": {
    "repos": [
      "gitops-certification-examples",
      "kdemo",
      "sunbird-data-pipeline",
      "ckh",
      "workshop-pulsar",
      "spring-petclinic",
      "mlops-on-gcp",
      "chaostoolkit-oci",
      "app-modernization-using-IBM-toolchain",
      "heungheung",
      "weblogic-operator-tutorialx",
      "idcs-byoa-php",
      "cndoke",
      "okeight",
      "PointsCollection",
      "WorkBetter",
      "CafeSupremo",
      "twitter-feed",
      "aura-js-creditscore-v2",
      "aura-js-creditscore",
      "angular-node-creditscore",
      "aura-tutorials",
      "learning-library",
      "CloudNative_Mobile",
      "LoyaltyManagement",
      "cloud-native-devops-workshop"
    ],
    "followers": [],
    "following": [
      "sachin-pikle",
      "shaunsmith",
      "nagypeter",
      "luisw19",
      "hyder"
    ]
  },
  "emails": []
}