{
  "wburgers": {
    "repos": [
      "lovelace-auto-entities",
      "ESPHomeRoombaComponent",
      "Session-Binding-Proxy",
      "play-liquibase",
      "postgres-docker",
      "ESP-Smart-Meter",
      "Home-AssistantConfig",
      "websocket-component",
      "wburgers.github.io",
      "OZWSS-Polymer-device-item",
      "trein-vertrektijden",
      "weather-component",
      "Open-Zwave-Socket-Server",
      "OZWSS-Polymer-single-room",
      "OZWSS-Polymer-scene-list-item",
      "OZWSS-Polymer-status-dot",
      "google-slides",
      "OZWSS-Polymer-google-signin-status",
      "OZWSS-Polymer-switch-button",
      "OZWSS-Polymer-scene-list",
      "OZWSS-Polymer-room-list-item",
      "OZWSS-Polymer-room-list",
      "SWS2-headless-browser",
      "Z-Droid"
    ],
    "followers": [],
    "following": [
      "devinhedge",
      "plugwise",
      "WM-Knikker",
      "jaspervanduijnhoven",
      "mkreijkes",
      "floriskruisselbrink",
      "nmrsmn",
      "vincentheet",
      "jonathanjuursema",
      "adebruijn1",
      "ChrisBrandhorst",
      "wampiedriessen",
      "Ruud-Wiegers",
      "TheCardinal",
      "luukdobber",
      "pbtcjasper",
      "Mattias1",
      "koenekelschot",
      "mrngm",
      "Knoop",
      "joostrijneveld",
      "lscholten"
    ]
  },
  "emails": []
}